django_logbasecommand-0.0.5.dist-info/licenses/LICENSE
logbasecommand/__init__.py
logbasecommand/base.py
django_logbasecommand-0.0.5.dist-info/METADATA
django_logbasecommand-0.0.5.dist-info/WHEEL
django_logbasecommand-0.0.5.dist-info/top_level.txt
django_logbasecommand-0.0.5.dist-info/RECORD
