Metadata-Version: 2.4
Name: django-logbasecommand
Version: 0.0.5
Summary: Minimal package to add logging helpers to Django management commands
Home-page: https://github.com/surface-security/django-logbasecommand/
Author: PPB - InfoSec Engineering
Author-email: surface@paddypowerbetfair.com
License: MIT
Classifier: Development Status :: 5 - Production/Stable
Classifier: Framework :: Django
Classifier: License :: OSI Approved :: MIT License
Classifier: Intended Audience :: Developers
Classifier: Operating System :: OS Independent
Classifier: Programming Language :: Python
Classifier: Programming Language :: Python :: 3.9
Classifier: Environment :: Web Environment
Classifier: Topic :: Software Development
Requires-Python: >=3.9
License-File: LICENSE
Requires-Dist: Django<6,>=3.0
Dynamic: license-file
